data_platform_helpers/__init__.py
data_platform_helpers/advanced_statuses/__init__.py
data_platform_helpers/advanced_statuses/components.py
data_platform_helpers/advanced_statuses/handler.py
data_platform_helpers/advanced_statuses/models.py
data_platform_helpers/advanced_statuses/protocol.py
data_platform_helpers/advanced_statuses/types.py
data_platform_helpers/advanced_statuses/utils.py
data_platform_helpers/tests_helpers/__init__.py
data_platform_helpers/tests_helpers/k8s/ha_helpers.py
data_platform_helpers/tests_helpers/vms/ha_helpers.py
data_platform_helpers/version_check.py
data_platform_helpers-0.1.7.dist-info/LICENSE
data_platform_helpers-0.1.7.dist-info/METADATA
data_platform_helpers-0.1.7.dist-info/WHEEL
data_platform_helpers-0.1.7.dist-info/RECORD
