Metadata-Version: 2.3
Name: data-platform-helpers
Version: 0.1.7
Summary: 
Author: Mia Altieri
Author-email: mgaltier200@gmail.com
Requires-Python: >=3.10,<4.0
Classifier: Programming Language :: Python :: 3
Classifier: Programming Language :: Python :: 3.10
Classifier: Programming Language :: Python :: 3.11
Classifier: Programming Language :: Python :: 3.12
Classifier: Programming Language :: Python :: 3.13
Provides-Extra: all
Provides-Extra: tests
Requires-Dist: ops (>=2.15.0)
Requires-Dist: pydantic (>=2.0)
Requires-Dist: pytest_operator (==0.36.0) ; extra == "tests" or extra == "all"
Requires-Dist: rich
